SimpleCache/SimpleCache.py
SimpleCache/__init__.py
cyclip_simplecache-1.1.2.dist-info/LICENSE
cyclip_simplecache-1.1.2.dist-info/METADATA
cyclip_simplecache-1.1.2.dist-info/WHEEL
cyclip_simplecache-1.1.2.dist-info/top_level.txt
cyclip_simplecache-1.1.2.dist-info/RECORD
