Metadata-Version: 2.1
Name: cyclip-simplecache
Version: 1.1.2
Summary: Pure-python implementation of Least Recently Used (LRU) caching. It allows a developer to easily use memoization on expensive function calls.
Home-page: https://github.com/Cyclip/SimpleCache
Author: Cyclip
License: MIT
Platform: UNKNOWN
Classifier: License :: OSI Approved :: MIT License
Classifier: Programming Language :: Python :: 3
Classifier: Programming Language :: Python :: 3.7
